baserow/__init__.py
baserow/client.py
baserow/field_types.py
baserow/field_types_test.py
baserow/filter.py
baserow/orm/__init__.py
baserow/orm/__main__.py
baserow/orm/column.py
baserow/orm/database.py
baserow/orm/exc.py
baserow/orm/mapping.py
baserow/orm/model.py
baserow/py.typed
baserow/types.py
baserow_client-0.6.0.dist-info/LICENSE
baserow_client-0.6.0.dist-info/METADATA
baserow_client-0.6.0.dist-info/WHEEL
baserow_client-0.6.0.dist-info/RECORD
