Metadata-Version: 2.1
Name: baserow-client
Version: 0.6.0
Summary: Client for the baserow.io API.
License: MIT
Author: Niklas Rosenstein
Author-email: rosensteinniklas@gmail.com
Requires-Python: >=3.8,<4.0
Classifier: License :: OSI Approved :: MIT License
Classifier: Programming Language :: Python :: 3
Classifier: Programming Language :: Python :: 3.8
Classifier: Programming Language :: Python :: 3.9
Classifier: Programming Language :: Python :: 3.10
Classifier: Programming Language :: Python :: 3.11
Requires-Dist: databind.core (>=4.2.5,<5.0.0)
Requires-Dist: databind.json (>=4.2.5,<5.0.0)
Requires-Dist: requests (>=2.26.0,<3.0.0)
Requires-Dist: typing-extensions (>=3.0.0)
Project-URL: Homepage, https://github.com/NiklasRosenstein/python-baserow-client
